[
  {
    "timestamp": "09/19/2024, 1:31:53 AM",
    "count": 54,
    "title": "Krazycaterpillar available hw stocks",
    "interval": "0.5 min"
  },
  {
    "timestamp": "09/19/2024, 1:32:17 AM",
    "count": 54,
    "title": "Krazycaterpillar available hw stocks",
    "interval": "0.5 min"
  },
  {
    "timestamp": "09/19/2024, 1:32:47 AM",
    "count": 54,
    "title": "Krazycaterpillar available hw stocks",
    "interval": "0.5 min"
  },
  {
    "timestamp": "09/19/2024, 10:28:08 AM",
    "count": 58,
    "title": "Krazycaterpillar available hw stocks",
    "interval": "0.5 min"
  },
  {
    "timestamp": "09/19/2024, 10:28:37 AM",
    "count": 58,
    "title": "Krazycaterpillar available hw stocks",
    "interval": "0.5 min"
  },
  {
    "timestamp": "09/19/2024, 10:28:47 AM",
    "count": 58,
    "title": "Krazycaterpillar available hw stocks",
    "interval": "10 min"
  },
  {
    "timestamp": "09/19/2024, 10:38:48 AM",
    "count": 58,
    "title": "Krazycaterpillar available hw stocks",
    "interval": "10 min"
  },
  {
    "timestamp": "09/19/2024, 10:48:48 AM",
    "count": 58,
    "title": "Krazycaterpillar available hw stocks",
    "interval": "10 min"
  },
  {
    "timestamp": "09/19/2024, 10:58:49 AM",
    "count": 58,
    "title": "Krazycaterpillar available hw stocks",
    "interval": "10 min"
  },
  {
    "timestamp": "09/19/2024, 11:10:29 AM",
    "count": 58,
    "title": "Krazycaterpillar available hw stocks",
    "interval": "10 min"
  },
  {
    "timestamp": "09/19/2024, 11:25:07 AM",
    "count": 55,
    "title": "Krazycaterpillar available hw stocks",
    "interval": "10 min"
  },
  {
    "timestamp": "09/19/2024, 11:35:07 AM",
    "count": 55,
    "title": "Krazycaterpillar available hw stocks",
    "interval": "10 min"
  },
  {
    "timestamp": "09/19/2024, 12:17:38 PM",
    "count": 55,
    "title": "Krazycaterpillar available hw stocks",
    "interval": "10 min"
  },
  {
    "timestamp": "09/19/2024, 12:27:38 PM",
    "count": 55,
    "title": "Krazycaterpillar available hw stocks",
    "interval": "10 min"
  },
  {
    "timestamp": "09/19/2024, 12:37:39 PM",
    "count": 55,
    "title": "Krazycaterpillar available hw stocks",
    "interval": "10 min"
  },
  {
    "timestamp": "09/19/2024, 12:47:38 PM",
    "count": 54,
    "title": "Krazycaterpillar available hw stocks",
    "interval": "10 min"
  },
  {
    "timestamp": "09/19/2024, 12:57:38 PM",
    "count": 54,
    "title": "Krazycaterpillar available hw stocks",
    "interval": "10 min"
  },
  {
    "timestamp": "09/19/2024, 1:07:38 PM",
    "count": 54,
    "title": "Krazycaterpillar available hw stocks",
    "interval": "10 min"
  },
  {
    "timestamp": "09/19/2024, 1:17:38 PM",
    "count": 54,
    "title": "Krazycaterpillar available hw stocks",
    "interval": "10 min"
  },
  {
    "timestamp": "09/19/2024, 1:27:38 PM",
    "count": 54,
    "title": "Krazycaterpillar available hw stocks",
    "interval": "10 min"
  },
  {
    "timestamp": "09/19/2024, 1:37:38 PM",
    "count": 54,
    "title": "Krazycaterpillar available hw stocks",
    "interval": "10 min"
  },
  {
    "timestamp": "09/19/2024, 1:47:38 PM",
    "count": 54,
    "title": "Krazycaterpillar available hw stocks",
    "interval": "10 min"
  },
  {
    "timestamp": "09/19/2024, 2:11:40 PM",
    "count": 54,
    "title": "Krazycaterpillar available hw stocks",
    "interval": "10 min"
  },
  {
    "timestamp": "09/19/2024, 2:25:41 PM",
    "count": 54,
    "title": "Krazycaterpillar available hw stocks",
    "interval": "10 min"
  },
  {
    "timestamp": "09/19/2024, 2:42:44 PM",
    "count": 54,
    "title": "Krazycaterpillar available hw stocks",
    "interval": "10 min"
  },
  {
    "timestamp": "09/19/2024, 3:03:13 PM",
    "count": 54,
    "title": "Krazycaterpillar available hw stocks",
    "interval": "10 min"
  },
  {
    "timestamp": "09/19/2024, 3:18:07 PM",
    "count": 54,
    "title": "Krazycaterpillar available hw stocks",
    "interval": "10 min"
  },
  {
    "timestamp": "09/19/2024, 3:36:51 PM",
    "count": 54,
    "title": "Krazycaterpillar available hw stocks",
    "interval": "10 min"
  },
  {
    "timestamp": "09/19/2024, 3:53:31 PM",
    "count": 54,
    "title": "Krazycaterpillar available hw stocks",
    "interval": "10 min"
  },
  {
    "timestamp": "09/19/2024, 4:03:31 PM",
    "count": 54,
    "title": "Krazycaterpillar available hw stocks",
    "interval": "10 min"
  },
  {
    "timestamp": "09/19/2024, 4:13:31 PM",
    "count": 54,
    "title": "Krazycaterpillar available hw stocks",
    "interval": "10 min"
  },
  {
    "timestamp": "09/19/2024, 4:23:32 PM",
    "count": 54,
    "title": "Krazycaterpillar available hw stocks",
    "interval": "10 min"
  },
  {
    "timestamp": "09/19/2024, 9:29:03 PM",
    "count": 80,
    "title": "Krazycaterpillar available hw stocks",
    "interval": "10 min"
  },
  {
    "timestamp": "09/19/2024, 9:35:33 PM",
    "count": 80,
    "title": "Krazycaterpillar available hw stocks",
    "interval": "1 min"
  },
  {
    "timestamp": "09/19/2024, 9:36:32 PM",
    "count": 80,
    "title": "Krazycaterpillar available hw stocks",
    "interval": "1 min"
  },
  {
    "timestamp": "09/19/2024, 9:37:32 PM",
    "count": 71,
    "title": "Krazycaterpillar available hw stocks",
    "interval": "1 min"
  },
  {
    "timestamp": "09/19/2024, 9:38:32 PM",
    "count": 71,
    "title": "Krazycaterpillar available hw stocks",
    "interval": "1 min"
  },
  {
    "timestamp": "09/19/2024, 9:39:33 PM",
    "count": 71,
    "title": "Krazycaterpillar available hw stocks",
    "interval": "1 min"
  },
  {
    "timestamp": "09/19/2024, 9:40:32 PM",
    "count": 71,
    "title": "Krazycaterpillar available hw stocks",
    "interval": "1 min"
  },
  {
    "timestamp": "09/19/2024, 9:41:32 PM",
    "count": 71,
    "title": "Krazycaterpillar available hw stocks",
    "interval": "1 min"
  },
  {
    "timestamp": "09/19/2024, 9:42:33 PM",
    "count": 71,
    "title": "Krazycaterpillar available hw stocks",
    "interval": "1 min"
  },
  {
    "timestamp": "09/19/2024, 9:43:32 PM",
    "count": 67,
    "title": "Krazycaterpillar available hw stocks",
    "interval": "1 min"
  },
  {
    "timestamp": "09/19/2024, 9:44:32 PM",
    "count": 67,
    "title": "Krazycaterpillar available hw stocks",
    "interval": "1 min"
  },
  {
    "timestamp": "09/19/2024, 9:45:32 PM",
    "count": 67,
    "title": "Krazycaterpillar available hw stocks",
    "interval": "1 min"
  },
  {
    "timestamp": "09/19/2024, 9:46:32 PM",
    "count": 67,
    "title": "Krazycaterpillar available hw stocks",
    "interval": "1 min"
  },
  {
    "timestamp": "09/19/2024, 9:47:32 PM",
    "count": 67,
    "title": "Krazycaterpillar available hw stocks",
    "interval": "1 min"
  },
  {
    "timestamp": "09/19/2024, 9:48:32 PM",
    "count": 67,
    "title": "Krazycaterpillar available hw stocks",
    "interval": "1 min"
  },
  {
    "timestamp": "09/19/2024, 9:49:34 PM",
    "count": 67,
    "title": "Krazycaterpillar available hw stocks",
    "interval": "1 min"
  },
  {
    "timestamp": "09/19/2024, 9:50:32 PM",
    "count": 67,
    "title": "Krazycaterpillar available hw stocks",
    "interval": "1 min"
  },
  {
    "timestamp": "09/19/2024, 9:51:33 PM",
    "count": 63,
    "title": "Krazycaterpillar available hw stocks",
    "interval": "1 min"
  },
  {
    "timestamp": "09/19/2024, 9:52:32 PM",
    "count": 63,
    "title": "Krazycaterpillar available hw stocks",
    "interval": "1 min"
  },
  {
    "timestamp": "09/19/2024, 9:53:31 PM",
    "count": 63,
    "title": "Krazycaterpillar available hw stocks",
    "interval": "1 min"
  },
  {
    "timestamp": "09/19/2024, 9:54:32 PM",
    "count": 63,
    "title": "Krazycaterpillar available hw stocks",
    "interval": "1 min"
  },
  {
    "timestamp": "09/19/2024, 9:55:33 PM",
    "count": 63,
    "title": "Krazycaterpillar available hw stocks",
    "interval": "1 min"
  },
  {
    "timestamp": "09/19/2024, 9:56:32 PM",
    "count": 63,
    "title": "Krazycaterpillar available hw stocks",
    "interval": "1 min"
  },
  {
    "timestamp": "09/19/2024, 9:57:32 PM",
    "count": 63,
    "title": "Krazycaterpillar available hw stocks",
    "interval": "1 min"
  },
  {
    "timestamp": "09/19/2024, 9:58:32 PM",
    "count": 63,
    "title": "Krazycaterpillar available hw stocks",
    "interval": "1 min"
  },
  {
    "timestamp": "09/19/2024, 9:59:33 PM",
    "count": 63,
    "title": "Krazycaterpillar available hw stocks",
    "interval": "1 min"
  },
  {
    "timestamp": "09/19/2024, 10:00:32 PM",
    "count": 63,
    "title": "Krazycaterpillar available hw stocks",
    "interval": "1 min"
  },
  {
    "timestamp": "09/19/2024, 10:01:32 PM",
    "count": 58,
    "title": "Krazycaterpillar available hw stocks",
    "interval": "1 min"
  },
  {
    "timestamp": "09/19/2024, 10:02:32 PM",
    "count": 58,
    "title": "Krazycaterpillar available hw stocks",
    "interval": "1 min"
  },
  {
    "timestamp": "09/19/2024, 10:03:32 PM",
    "count": 58,
    "title": "Krazycaterpillar available hw stocks",
    "interval": "1 min"
  },
  {
    "timestamp": "09/19/2024, 10:04:32 PM",
    "count": 58,
    "title": "Krazycaterpillar available hw stocks",
    "interval": "1 min"
  },
  {
    "timestamp": "09/19/2024, 10:05:33 PM",
    "count": 58,
    "title": "Krazycaterpillar available hw stocks",
    "interval": "1 min"
  },
  {
    "timestamp": "09/19/2024, 10:06:32 PM",
    "count": 58,
    "title": "Krazycaterpillar available hw stocks",
    "interval": "1 min"
  },
  {
    "timestamp": "09/19/2024, 10:07:33 PM",
    "count": 58,
    "title": "Krazycaterpillar available hw stocks",
    "interval": "1 min"
  },
  {
    "timestamp": "09/19/2024, 10:08:33 PM",
    "count": 58,
    "title": "Krazycaterpillar available hw stocks",
    "interval": "1 min"
  },
  {
    "timestamp": "09/19/2024, 10:09:32 PM",
    "count": 58,
    "title": "Krazycaterpillar available hw stocks",
    "interval": "1 min"
  },
  {
    "timestamp": "09/19/2024, 10:10:32 PM",
    "count": 58,
    "title": "Krazycaterpillar available hw stocks",
    "interval": "1 min"
  },
  {
    "timestamp": "09/19/2024, 10:11:32 PM",
    "count": 58,
    "title": "Krazycaterpillar available hw stocks",
    "interval": "1 min"
  },
  {
    "timestamp": "09/19/2024, 10:12:32 PM",
    "count": 58,
    "title": "Krazycaterpillar available hw stocks",
    "interval": "1 min"
  },
  {
    "timestamp": "09/19/2024, 10:13:33 PM",
    "count": 58,
    "title": "Krazycaterpillar available hw stocks",
    "interval": "1 min"
  },
  {
    "timestamp": "09/19/2024, 10:14:32 PM",
    "count": 58,
    "title": "Krazycaterpillar available hw stocks",
    "interval": "1 min"
  },
  {
    "timestamp": "09/19/2024, 10:15:33 PM",
    "count": 58,
    "title": "Krazycaterpillar available hw stocks",
    "interval": "1 min"
  },
  {
    "timestamp": "09/19/2024, 10:16:32 PM",
    "count": 58,
    "title": "Krazycaterpillar available hw stocks",
    "interval": "1 min"
  },
  {
    "timestamp": "09/19/2024, 10:17:32 PM",
    "count": 58,
    "title": "Krazycaterpillar available hw stocks",
    "interval": "1 min"
  },
  {
    "timestamp": "09/19/2024, 10:18:33 PM",
    "count": 58,
    "title": "Krazycaterpillar available hw stocks",
    "interval": "1 min"
  },
  {
    "timestamp": "09/19/2024, 10:19:32 PM",
    "count": 58,
    "title": "Krazycaterpillar available hw stocks",
    "interval": "1 min"
  },
  {
    "timestamp": "09/19/2024, 10:20:33 PM",
    "count": 58,
    "title": "Krazycaterpillar available hw stocks",
    "interval": "1 min"
  },
  {
    "timestamp": "09/19/2024, 10:21:32 PM",
    "count": 58,
    "title": "Krazycaterpillar available hw stocks",
    "interval": "1 min"
  },
  {
    "timestamp": "09/19/2024, 10:22:32 PM",
    "count": 58,
    "title": "Krazycaterpillar available hw stocks",
    "interval": "1 min"
  },
  {
    "timestamp": "09/19/2024, 10:23:32 PM",
    "count": 58,
    "title": "Krazycaterpillar available hw stocks",
    "interval": "1 min"
  },
  {
    "timestamp": "09/19/2024, 10:24:33 PM",
    "count": 58,
    "title": "Krazycaterpillar available hw stocks",
    "interval": "1 min"
  },
  {
    "timestamp": "09/19/2024, 10:25:32 PM",
    "count": 58,
    "title": "Krazycaterpillar available hw stocks",
    "interval": "1 min"
  },
  {
    "timestamp": "09/19/2024, 10:26:33 PM",
    "count": 58,
    "title": "Krazycaterpillar available hw stocks",
    "interval": "1 min"
  },
  {
    "timestamp": "09/19/2024, 10:27:32 PM",
    "count": 58,
    "title": "Krazycaterpillar available hw stocks",
    "interval": "1 min"
  },
  {
    "timestamp": "09/19/2024, 10:28:32 PM",
    "count": 58,
    "title": "Krazycaterpillar available hw stocks",
    "interval": "1 min"
  },
  {
    "timestamp": "09/19/2024, 10:29:33 PM",
    "count": 58,
    "title": "Krazycaterpillar available hw stocks",
    "interval": "1 min"
  },
  {
    "timestamp": "09/19/2024, 10:30:32 PM",
    "count": 58,
    "title": "Krazycaterpillar available hw stocks",
    "interval": "1 min"
  },
  {
    "timestamp": "09/19/2024, 10:31:33 PM",
    "count": 58,
    "title": "Krazycaterpillar available hw stocks",
    "interval": "1 min"
  },
  {
    "timestamp": "09/19/2024, 10:32:32 PM",
    "count": 56,
    "title": "Krazycaterpillar available hw stocks",
    "interval": "1 min"
  },
  {
    "timestamp": "09/19/2024, 10:33:33 PM",
    "count": 56,
    "title": "Krazycaterpillar available hw stocks",
    "interval": "1 min"
  },
  {
    "timestamp": "09/19/2024, 10:34:32 PM",
    "count": 56,
    "title": "Krazycaterpillar available hw stocks",
    "interval": "1 min"
  },
  {
    "timestamp": "09/19/2024, 10:35:31 PM",
    "count": 56,
    "title": "Krazycaterpillar available hw stocks",
    "interval": "1 min"
  },
  {
    "timestamp": "09/19/2024, 10:36:32 PM",
    "count": 56,
    "title": "Krazycaterpillar available hw stocks",
    "interval": "1 min"
  },
  {
    "timestamp": "09/19/2024, 10:37:32 PM",
    "count": 56,
    "title": "Krazycaterpillar available hw stocks",
    "interval": "1 min"
  },
  {
    "timestamp": "09/19/2024, 10:38:32 PM",
    "count": 56,
    "title": "Krazycaterpillar available hw stocks",
    "interval": "1 min"
  },
  {
    "timestamp": "09/19/2024, 10:39:32 PM",
    "count": 56,
    "title": "Krazycaterpillar available hw stocks",
    "interval": "1 min"
  },
  {
    "timestamp": "09/19/2024, 10:40:32 PM",
    "count": 56,
    "title": "Krazycaterpillar available hw stocks",
    "interval": "1 min"
  },
  {
    "timestamp": "09/19/2024, 10:41:32 PM",
    "count": 56,
    "title": "Krazycaterpillar available hw stocks",
    "interval": "1 min"
  },
  {
    "timestamp": "09/19/2024, 10:42:32 PM",
    "count": 56,
    "title": "Krazycaterpillar available hw stocks",
    "interval": "1 min"
  },
  {
    "timestamp": "09/19/2024, 10:43:33 PM",
    "count": 56,
    "title": "Krazycaterpillar available hw stocks",
    "interval": "1 min"
  },
  {
    "timestamp": "09/19/2024, 10:44:33 PM",
    "count": 56,
    "title": "Krazycaterpillar available hw stocks",
    "interval": "1 min"
  },
  {
    "timestamp": "09/19/2024, 10:45:32 PM",
    "count": 56,
    "title": "Krazycaterpillar available hw stocks",
    "interval": "1 min"
  },
  {
    "timestamp": "09/19/2024, 10:46:32 PM",
    "count": 56,
    "title": "Krazycaterpillar available hw stocks",
    "interval": "1 min"
  },
  {
    "timestamp": "09/19/2024, 10:47:32 PM",
    "count": 56,
    "title": "Krazycaterpillar available hw stocks",
    "interval": "1 min"
  },
  {
    "timestamp": "09/19/2024, 10:48:33 PM",
    "count": 56,
    "title": "Krazycaterpillar available hw stocks",
    "interval": "1 min"
  },
  {
    "timestamp": "09/19/2024, 10:49:33 PM",
    "count": 56,
    "title": "Krazycaterpillar available hw stocks",
    "interval": "1 min"
  },
  {
    "timestamp": "09/19/2024, 10:50:32 PM",
    "count": 56,
    "title": "Krazycaterpillar available hw stocks",
    "interval": "1 min"
  },
  {
    "timestamp": "09/19/2024, 10:51:33 PM",
    "count": 56,
    "title": "Krazycaterpillar available hw stocks",
    "interval": "1 min"
  },
  {
    "timestamp": "09/19/2024, 10:52:33 PM",
    "count": 56,
    "title": "Krazycaterpillar available hw stocks",
    "interval": "1 min"
  },
  {
    "timestamp": "09/19/2024, 10:53:33 PM",
    "count": 56,
    "title": "Krazycaterpillar available hw stocks",
    "interval": "1 min"
  },
  {
    "timestamp": "09/19/2024, 10:54:32 PM",
    "count": 56,
    "title": "Krazycaterpillar available hw stocks",
    "interval": "1 min"
  },
  {
    "timestamp": "09/19/2024, 10:55:33 PM",
    "count": 56,
    "title": "Krazycaterpillar available hw stocks",
    "interval": "1 min"
  },
  {
    "timestamp": "09/19/2024, 10:56:32 PM",
    "count": 56,
    "title": "Krazycaterpillar available hw stocks",
    "interval": "1 min"
  },
  {
    "timestamp": "09/19/2024, 10:57:33 PM",
    "count": 56,
    "title": "Krazycaterpillar available hw stocks",
    "interval": "1 min"
  },
  {
    "timestamp": "09/19/2024, 10:58:32 PM",
    "count": 56,
    "title": "Krazycaterpillar available hw stocks",
    "interval": "1 min"
  },
  {
    "timestamp": "09/19/2024, 10:59:33 PM",
    "count": 56,
    "title": "Krazycaterpillar available hw stocks",
    "interval": "1 min"
  },
  {
    "timestamp": "09/19/2024, 11:00:33 PM",
    "count": 56,
    "title": "Krazycaterpillar available hw stocks",
    "interval": "1 min"
  },
  {
    "timestamp": "09/19/2024, 11:01:33 PM",
    "count": 56,
    "title": "Krazycaterpillar available hw stocks",
    "interval": "1 min"
  },
  {
    "timestamp": "09/19/2024, 11:02:32 PM",
    "count": 56,
    "title": "Krazycaterpillar available hw stocks",
    "interval": "1 min"
  },
  {
    "timestamp": "09/19/2024, 11:03:33 PM",
    "count": 56,
    "title": "Krazycaterpillar available hw stocks",
    "interval": "1 min"
  },
  {
    "timestamp": "09/19/2024, 11:04:32 PM",
    "count": 56,
    "title": "Krazycaterpillar available hw stocks",
    "interval": "1 min"
  },
  {
    "timestamp": "09/19/2024, 11:05:32 PM",
    "count": 56,
    "title": "Krazycaterpillar available hw stocks",
    "interval": "1 min"
  },
  {
    "timestamp": "09/19/2024, 11:06:32 PM",
    "count": 56,
    "title": "Krazycaterpillar available hw stocks",
    "interval": "1 min"
  },
  {
    "timestamp": "09/19/2024, 11:07:34 PM",
    "count": 56,
    "title": "Krazycaterpillar available hw stocks",
    "interval": "1 min"
  },
  {
    "timestamp": "09/19/2024, 11:08:33 PM",
    "count": 56,
    "title": "Krazycaterpillar available hw stocks",
    "interval": "1 min"
  },
  {
    "timestamp": "09/19/2024, 11:09:32 PM",
    "count": 56,
    "title": "Krazycaterpillar available hw stocks",
    "interval": "1 min"
  },
  {
    "timestamp": "09/19/2024, 11:10:32 PM",
    "count": 56,
    "title": "Krazycaterpillar available hw stocks",
    "interval": "1 min"
  },
  {
    "timestamp": "09/19/2024, 11:11:33 PM",
    "count": 56,
    "title": "Krazycaterpillar available hw stocks",
    "interval": "1 min"
  },
  {
    "timestamp": "09/19/2024, 11:12:32 PM",
    "count": 56,
    "title": "Krazycaterpillar available hw stocks",
    "interval": "1 min"
  },
  {
    "timestamp": "09/19/2024, 11:13:33 PM",
    "count": 55,
    "title": "Krazycaterpillar available hw stocks",
    "interval": "1 min"
  },
  {
    "timestamp": "09/19/2024, 11:14:32 PM",
    "count": 55,
    "title": "Krazycaterpillar available hw stocks",
    "interval": "1 min"
  },
  {
    "timestamp": "09/19/2024, 11:15:33 PM",
    "count": 55,
    "title": "Krazycaterpillar available hw stocks",
    "interval": "1 min"
  },
  {
    "timestamp": "09/19/2024, 11:16:34 PM",
    "count": 55,
    "title": "Krazycaterpillar available hw stocks",
    "interval": "1 min"
  },
  {
    "timestamp": "09/19/2024, 11:17:33 PM",
    "count": 55,
    "title": "Krazycaterpillar available hw stocks",
    "interval": "1 min"
  },
  {
    "timestamp": "09/19/2024, 11:18:33 PM",
    "count": 55,
    "title": "Krazycaterpillar available hw stocks",
    "interval": "1 min"
  },
  {
    "timestamp": "09/19/2024, 11:19:33 PM",
    "count": 55,
    "title": "Krazycaterpillar available hw stocks",
    "interval": "1 min"
  },
  {
    "timestamp": "09/19/2024, 11:20:33 PM",
    "count": 55,
    "title": "Krazycaterpillar available hw stocks",
    "interval": "1 min"
  },
  {
    "timestamp": "09/19/2024, 11:21:33 PM",
    "count": 55,
    "title": "Krazycaterpillar available hw stocks",
    "interval": "1 min"
  },
  {
    "timestamp": "09/19/2024, 11:22:33 PM",
    "count": 55,
    "title": "Krazycaterpillar available hw stocks",
    "interval": "1 min"
  },
  {
    "timestamp": "09/19/2024, 11:23:33 PM",
    "count": 55,
    "title": "Krazycaterpillar available hw stocks",
    "interval": "1 min"
  },
  {
    "timestamp": "09/19/2024, 11:24:32 PM",
    "count": 55,
    "title": "Krazycaterpillar available hw stocks",
    "interval": "1 min"
  },
  {
    "timestamp": "09/19/2024, 11:25:33 PM",
    "count": 55,
    "title": "Krazycaterpillar available hw stocks",
    "interval": "1 min"
  },
  {
    "timestamp": "09/19/2024, 11:26:32 PM",
    "count": 55,
    "title": "Krazycaterpillar available hw stocks",
    "interval": "1 min"
  },
  {
    "timestamp": "09/19/2024, 11:27:33 PM",
    "count": 55,
    "title": "Krazycaterpillar available hw stocks",
    "interval": "1 min"
  },
  {
    "timestamp": "09/19/2024, 11:28:32 PM",
    "count": 55,
    "title": "Krazycaterpillar available hw stocks",
    "interval": "1 min"
  },
  {
    "timestamp": "09/19/2024, 11:29:32 PM",
    "count": 55,
    "title": "Krazycaterpillar available hw stocks",
    "interval": "1 min"
  },
  {
    "timestamp": "09/19/2024, 11:30:33 PM",
    "count": 55,
    "title": "Krazycaterpillar available hw stocks",
    "interval": "1 min"
  },
  {
    "timestamp": "09/19/2024, 11:31:32 PM",
    "count": 55,
    "title": "Krazycaterpillar available hw stocks",
    "interval": "1 min"
  },
  {
    "timestamp": "09/19/2024, 11:32:32 PM",
    "count": 55,
    "title": "Krazycaterpillar available hw stocks",
    "interval": "1 min"
  },
  {
    "timestamp": "09/19/2024, 11:33:33 PM",
    "count": 55,
    "title": "Krazycaterpillar available hw stocks",
    "interval": "1 min"
  },
  {
    "timestamp": "09/19/2024, 11:34:33 PM",
    "count": 55,
    "title": "Krazycaterpillar available hw stocks",
    "interval": "1 min"
  },
  {
    "timestamp": "09/19/2024, 11:35:33 PM",
    "count": 55,
    "title": "Krazycaterpillar available hw stocks",
    "interval": "1 min"
  },
  {
    "timestamp": "09/19/2024, 11:36:33 PM",
    "count": 55,
    "title": "Krazycaterpillar available hw stocks",
    "interval": "1 min"
  },
  {
    "timestamp": "09/19/2024, 11:37:32 PM",
    "count": 55,
    "title": "Krazycaterpillar available hw stocks",
    "interval": "1 min"
  },
  {
    "timestamp": "09/19/2024, 11:38:32 PM",
    "count": 55,
    "title": "Krazycaterpillar available hw stocks",
    "interval": "1 min"
  },
  {
    "timestamp": "09/19/2024, 11:39:32 PM",
    "count": 55,
    "title": "Krazycaterpillar available hw stocks",
    "interval": "1 min"
  },
  {
    "timestamp": "09/19/2024, 11:40:33 PM",
    "count": 55,
    "title": "Krazycaterpillar available hw stocks",
    "interval": "1 min"
  },
  {
    "timestamp": "09/19/2024, 11:41:33 PM",
    "count": 55,
    "title": "Krazycaterpillar available hw stocks",
    "interval": "1 min"
  },
  {
    "timestamp": "09/19/2024, 11:42:33 PM",
    "count": 55,
    "title": "Krazycaterpillar available hw stocks",
    "interval": "1 min"
  },
  {
    "timestamp": "09/19/2024, 11:43:31 PM",
    "count": 55,
    "title": "Krazycaterpillar available hw stocks",
    "interval": "1 min"
  },
  {
    "timestamp": "09/19/2024, 11:44:33 PM",
    "count": 55,
    "title": "Krazycaterpillar available hw stocks",
    "interval": "1 min"
  },
  {
    "timestamp": "09/19/2024, 11:45:32 PM",
    "count": 55,
    "title": "Krazycaterpillar available hw stocks",
    "interval": "1 min"
  },
  {
    "timestamp": "09/19/2024, 11:46:33 PM",
    "count": 55,
    "title": "Krazycaterpillar available hw stocks",
    "interval": "1 min"
  },
  {
    "timestamp": "09/19/2024, 11:47:33 PM",
    "count": 55,
    "title": "Krazycaterpillar available hw stocks",
    "interval": "1 min"
  },
  {
    "timestamp": "09/19/2024, 11:48:33 PM",
    "count": 55,
    "title": "Krazycaterpillar available hw stocks",
    "interval": "1 min"
  },
  {
    "timestamp": "09/19/2024, 11:49:32 PM",
    "count": 55,
    "title": "Krazycaterpillar available hw stocks",
    "interval": "1 min"
  },
  {
    "timestamp": "09/19/2024, 11:50:33 PM",
    "count": 55,
    "title": "Krazycaterpillar available hw stocks",
    "interval": "1 min"
  },
  {
    "timestamp": "09/19/2024, 11:51:33 PM",
    "count": 55,
    "title": "Krazycaterpillar available hw stocks",
    "interval": "1 min"
  },
  {
    "timestamp": "09/19/2024, 11:52:33 PM",
    "count": 55,
    "title": "Krazycaterpillar available hw stocks",
    "interval": "1 min"
  },
  {
    "timestamp": "09/19/2024, 11:53:32 PM",
    "count": 55,
    "title": "Krazycaterpillar available hw stocks",
    "interval": "1 min"
  },
  {
    "timestamp": "09/19/2024, 11:54:33 PM",
    "count": 55,
    "title": "Krazycaterpillar available hw stocks",
    "interval": "1 min"
  },
  {
    "timestamp": "09/19/2024, 11:55:32 PM",
    "count": 55,
    "title": "Krazycaterpillar available hw stocks",
    "interval": "1 min"
  }
]